video_process/__init__.py
video_process/graph_builder.py
video_process/index.py
video_process/lib.py
video_process/subtitle.py
video_process/utils.py
video_process-0.2.6.dist-info/METADATA
video_process-0.2.6.dist-info/WHEEL
video_process-0.2.6.dist-info/RECORD
