Metadata-Version: 2.1
Name: video-process
Version: 0.2.6
Summary: A package for video processing
Author: shao wei
Author-email: shaowei_8910@163.com
Requires-Python: >=3.10,<4.0
Classifier: Programming Language :: Python :: 3
Classifier: Programming Language :: Python :: 3.10
Classifier: Programming Language :: Python :: 3.11
